commandpy/__init__.py
commandpy/command.py
commandpy/engine.py
commandpy/exceptions.py
commandpy/group.py
commandpy/injectcommand.py
commandpy/injected_command.py
commandpy/parse.py
commandpy/protocols.py
commandpy-0.2.0.dist-info/WHEEL
commandpy-0.2.0.dist-info/METADATA
commandpy-0.2.0.dist-info/RECORD
