Metadata-Version: 2.1
Name: commandpy
Version: 0.2.0
Summary: 
Author: iRedSC
Requires-Python: >=3.10,<4.0
Classifier: Programming Language :: Python :: 3
Classifier: Programming Language :: Python :: 3.10
Requires-Dist: tokenstream (>=1.4.2,<2.0.0)
